pygrapher/__init__.py
pygrapher/__main__.py
pygrapher/equations.py
pygrapher/grapher.py
pygrapher/runner.py
test/__init__.py
test/test_grapher.py
test/test_runner.py
pygrapher-0.0.1.dist-info/LICENSE
pygrapher-0.0.1.dist-info/METADATA
pygrapher-0.0.1.dist-info/WHEEL
pygrapher-0.0.1.dist-info/top_level.txt
pygrapher-0.0.1.dist-info/RECORD
